{
  "name": "clinical_assertion",
  "columns": [
    {
      "name": "id",
      "datatype": "string"
    },
    {
      "name": "accession",
      "datatype": "string"
    },
    {
      "name": "version",
      "datatype": "integer"
    },
    {
      "name": "title",
      "datatype": "string"
    },
    {
      "name": "local_key",
      "datatype": "string"
    },
    {
      "name": "assertion_type",
      "datatype": "string"
    },
    {
      "name": "date_created",
      "datatype": "date"
    },
    {
      "name": "date_last_updated",
      "datatype": "date"
    },
    {
      "name": "submitted_assembly",
      "datatype": "string"
    },
    {
      "name": "record_status",
      "datatype": "string"
    },
    {
      "name": "review_status",
      "datatype": "string"
    },
    {
      "name": "interp_description",
      "datatype": "string"
    },
    {
      "name": "interp_date_last_evaluated",
      "datatype": "date"
    },
    {
      "name": "interp_explanation_of_interp",
      "datatype": "string"
    },
    {
      "name": "interp_comment",
      "datatype": "string"
    },
    {
      "name": "interp_comment_type",
      "datatype": "string"
    },
    {
      "name": "content",
      "datatype": "string"
    },
    {
      "name": "rcv_accession_id",
      "datatype": "string",
      "links": [
        {
          "table_name": "rcv_accession",
          "column_name": "id"
        }
      ]
    },
    {
      "name": "variation_archive_id",
      "datatype": "string",
      "links": [
        {
          "table_name": "variation_archive",
          "column_name": "id"
        }
      ]
    },
    {
      "name": "variation_archive_variation_id",
      "datatype": "integer",
      "links": [
        {
          "table_name": "variation_archive_variation",
          "column_name": "id"
        }
      ]
    }
  ]
}
